[
  {
    "id": "fashion_basic",
    "name": "패션 기본 마진",
    "description": "패션의류 기본 마진율 적용",
    "strategy": "fixed_margin",
    "base_margin": 0.4,
    "min_margin": 0.2,
    "max_margin": 0.6,
    "rounding_rule": "nine_ending",
    "supplier_ids": [],
    "category_codes": [
      "FASHION",
      "FASHION_WOMEN",
      "FASHION_MEN"
    ],
    "min_cost": null,
    "max_cost": null,
    "volume_discount": false,
    "seasonal_adjustment": false,
    "competition_factor": 1.0,
    "priority": 10,
    "active": true,
    "created_at": "2025-07-05T18:41:53.165397",
    "updated_at": "2025-07-05T18:41:53.165400"
  },
  {
    "id": "beauty_premium",
    "name": "뷰티 프리미엄 마진",
    "description": "뷰티 상품 프리미엄 마진율 적용",
    "strategy": "premium",
    "base_margin": 0.5,
    "min_margin": 0.3,
    "max_margin": 0.7,
    "rounding_rule": "nine_ending",
    "supplier_ids": [],
    "category_codes": [
      "BEAUTY"
    ],
    "min_cost": null,
    "max_cost": null,
    "volume_discount": false,
    "seasonal_adjustment": false,
    "competition_factor": 1.0,
    "priority": 15,
    "active": true,
    "created_at": "2025-07-05T18:41:53.165405",
    "updated_at": "2025-07-05T18:41:53.165405"
  },
  {
    "id": "electronics_competitive",
    "name": "전자제품 경쟁 가격",
    "description": "전자제품 경쟁력 있는 가격 책정",
    "strategy": "competitive",
    "base_margin": 0.15,
    "min_margin": 0.05,
    "max_margin": 0.25,
    "rounding_rule": "thousand",
    "supplier_ids": [],
    "category_codes": [
      "ELECTRONICS"
    ],
    "min_cost": null,
    "max_cost": null,
    "volume_discount": false,
    "seasonal_adjustment": false,
    "competition_factor": 0.95,
    "priority": 20,
    "active": true,
    "created_at": "2025-07-05T18:41:53.165408",
    "updated_at": "2025-07-05T18:41:53.165409"
  },
  {
    "id": "low_price_high_margin",
    "name": "저가 상품 고마진",
    "description": "저가 상품에 높은 마진율 적용",
    "strategy": "fixed_margin",
    "base_margin": 0.6,
    "min_margin": 0.4,
    "max_margin": 0.8,
    "rounding_rule": "nine_ending",
    "supplier_ids": [],
    "category_codes": [],
    "min_cost": "1000",
    "max_cost": "10000",
    "volume_discount": false,
    "seasonal_adjustment": false,
    "competition_factor": 1.0,
    "priority": 5,
    "active": true,
    "created_at": "2025-07-05T18:41:53.165413",
    "updated_at": "2025-07-05T18:41:53.165413"
  },
  {
    "id": "high_price_low_margin",
    "name": "고가 상품 저마진",
    "description": "고가 상품에 낮은 마진율 적용",
    "strategy": "fixed_margin",
    "base_margin": 0.2,
    "min_margin": 0.1,
    "max_margin": 0.3,
    "rounding_rule": "thousand",
    "supplier_ids": [],
    "category_codes": [],
    "min_cost": "100000",
    "max_cost": null,
    "volume_discount": false,
    "seasonal_adjustment": false,
    "competition_factor": 1.0,
    "priority": 5,
    "active": true,
    "created_at": "2025-07-05T18:41:53.165422",
    "updated_at": "2025-07-05T18:41:53.165422"
  },
  {
    "id": "domeme_standard",
    "name": "도매매 표준 마진",
    "description": "도매매 공급사 표준 마진율",
    "strategy": "fixed_margin",
    "base_margin": 0.35,
    "min_margin": 0.2,
    "max_margin": 0.5,
    "rounding_rule": "nine_ending",
    "supplier_ids": [
      "domeme"
    ],
    "category_codes": [],
    "min_cost": null,
    "max_cost": null,
    "volume_discount": false,
    "seasonal_adjustment": false,
    "competition_factor": 1.0,
    "priority": 8,
    "active": true,
    "created_at": "2025-07-05T18:41:53.165425",
    "updated_at": "2025-07-05T18:41:53.165425"
  },
  {
    "id": "dynamic_adjustment",
    "name": "동적 가격 조정",
    "description": "시장 상황에 따른 동적 가격 조정",
    "strategy": "dynamic",
    "base_margin": 0.3,
    "min_margin": 0.15,
    "max_margin": 0.45,
    "rounding_rule": "nine_ending",
    "supplier_ids": [],
    "category_codes": [],
    "min_cost": null,
    "max_cost": null,
    "volume_discount": true,
    "seasonal_adjustment": true,
    "competition_factor": 1.0,
    "priority": 1,
    "active": true,
    "created_at": "2025-07-05T18:41:53.165428",
    "updated_at": "2025-07-05T18:41:53.165428"
  }
]